README.md
setup.py
Freya_alerce/__init__.py
Freya_alerce/freya.py
Freya_alerce.egg-info/PKG-INFO
Freya_alerce.egg-info/SOURCES.txt
Freya_alerce.egg-info/dependency_links.txt
Freya_alerce.egg-info/entry_points.txt
Freya_alerce.egg-info/not-zip-safe
Freya_alerce.egg-info/requires.txt
Freya_alerce.egg-info/top_level.txt
Freya_alerce/catalogs/__init__.py
Freya_alerce/catalogs/PS1/__init__.py
Freya_alerce/catalogs/PS1/configure.py
Freya_alerce/catalogs/ZTF/__init__.py
Freya_alerce/catalogs/ZTF/configure.py
Freya_alerce/catalogs/core/__init__.py
Freya_alerce/catalogs/core/abstract_catalog.py
Freya_alerce/catalogs/core/core.py
Freya_alerce/catalogs/core/data_lc.py
Freya_alerce/catalogs/core/format_lc.py
Freya_alerce/core/__init__.py
Freya_alerce/core/utils.py
Freya_alerce/core/commands/__init__.py
Freya_alerce/core/commands/addcatalog.py
Freya_alerce/core/commands/addcataloglocal.py
Freya_alerce/core/commands/addresource.py
Freya_alerce/core/commands/base_api.py
Freya_alerce/core/commands/base_freya.py
Freya_alerce/core/commands/deletecatalog.py
Freya_alerce/core/commands/newapi.py
Freya_alerce/core/commands/renamecatalog.py
Freya_alerce/files/__init__.py
Freya_alerce/files/list_file.py
Freya_alerce/files/verify_file.py
Freya_alerce/files/file_templates/__init__.py
Freya_alerce/files/file_templates/from_.zip
Freya_alerce/files/file_templates/newresource.zip
Freya_alerce/files/file_templates/path_file_templates.py
tests/__init__.py
tests/test_add_resource.py
tests/test_create_api.py
tests/test_create_module_api.py
tests/test_create_module_local_api.py
tests/test_delete_catalog.py
tests/test_import.py
tests/test_list_files.py
tests/test_methods_get_data.py
tests/test_rename_catalog.py
tests/test_utils_transform.py
tests/test_verify_file.py