Metadata-Version: 1.2
Name: Freya-alerce
Version: 0.2.1
Summary: Freya is a Python framework that quick development queries in astronomical catalogs and use local or creating easy new API called FreyaAPI
Home-page: https://github.com/fernandezeric/Freya
Author: Eric "Jonimott" Fernández
Author-email: 
License: UNKNOWN
Platform: UNKNOWN
Classifier: Programming Language :: Python :: 3.9
Classifier: Operating System :: OS Independent
Classifier: Development Status :: 4 - Beta
Classifier: Natural Language :: English
Requires-Python: >=3.9
